mem_1kB.v
`timescale 1ns/1ns

module mem_1kB (
    input        clk,
    input        rst,
    input        wr,
    input  [7:0] data_in,
    input  [9:0] address,
    output reg [7:0] data_out
);

    reg [7:0] mem [0:1023];

    always @(posedge clk) begin

        if (rst) begin
            data_out <= 8'b0;
        end
        else begin

            if (wr) begin
                mem[address] <= data_in;
            end
            else begin
                data_out <= mem[address];
            end

        end

    end

endmodule

mem_1kB_tb.v
`timescale 1ns/1ns
module mem_1kB_tb;
    reg clk;
    reg rst;
    reg  wr;
    reg [7:0]  data_in;
    reg [9:0]  address;
    wire [7:0] data_out;
    // DUT
    mem_1kB uut (
        .clk      (clk),
        .rst      (rst),
        .wr       (wr),
        .data_in  (data_in),
        .address  (address),
        .data_out (data_out)
    );

    // CLOCK GENERATION  Period = 10 ns

    initial begin
        clk = 0;

        forever #5 clk = ~clk;
    end

    initial begin
        // INITIAL VALUES

        rst     = 1;
        wr      = 0;
        data_in = 8'd0;
        address = 10'd0;

        // RESET
        @(negedge clk);
        rst = 1;
        @(posedge clk);
        // $strobe prints AFTER NBA update
        $strobe("%0t ns : RESET      : data_out = %0d", $time, data_out);

        // RELEASE RESET

        @(negedge clk);
        rst = 0;

        // WRITE 10 TO ADDRESS 103

        @(negedge clk);
        wr      = 1;
        address = 10'd103;
        data_in = 8'd10;
        @(posedge clk);
        $strobe("%0t ns : WRITE      : address = %0d, data = %0d",  $time, address, data_in);

        // WRITE 134 TO ADDRESS 104
        @(negedge clk);
        wr      = 1;
        address = 10'd104;
        data_in = 8'd134;
        @(posedge clk);
        $strobe("%0t ns : WRITE      : address = %0d, data = %0d",  $time, address, data_in);

        // READ ADDRESS 103
        // Expected: 10
    
        @(negedge clk);
        wr      = 0;
        address = 10'd103;
        @(posedge clk);
        $strobe("%0t ns : READ       : address = %0d, data_out = %0d", $time, address, data_out);

        // READ ADDRESS 3
        // Expected: X
        // Because address 3 was never written
        @(negedge clk);
        wr      = 0;
        address = 10'd3;
        @(posedge clk);
        $strobe("%0t ns : READ       : address = %0d, data_out = %0d", $time, address, data_out);

        // WRITE 102 TO ADDRESS 103
        @(negedge clk);
        wr      = 1;
        address = 10'd103;
        data_in = 8'd102;
        @(posedge clk);
        $strobe("%0t ns : WRITE      : address = %0d, data = %0d",  $time, address, data_in);

        // READ ADDRESS 103 AGAIN
        // Expected: 102

        @(negedge clk);
        wr      = 0;
        address = 10'd103;
        @(posedge clk);
        $strobe("%0t ns : READ       : address = %0d, data_out = %0d", $time, address, data_out);
         
        // FINISH
        #10;
        $finish;
        end
        initial begin
        $dumpfile("mem_1kB_tb.vcd");
        $dumpvars(0, mem_1kB_tb);
        end
endmodule

mem_1kB_tb.vcd
$date
	Tue Sep  1 19:09:56 2026
$end
$version
	Icarus Verilog
$end
$timescale
	1ns
$end
$scope module mem_1kB_tb $end
$var wire 8 ! data_out [7:0] $end
$var reg 10 " address [9:0] $end
$var reg 1 # clk $end
$var reg 8 $ data_in [7:0] $end
$var reg 1 % rst $end
$var reg 1 & wr $end
$scope module uut $end
$var wire 10 ' address [9:0] $end
$var wire 1 # clk $end
$var wire 8 ( data_in [7:0] $end
$var wire 1 % rst $end
$var wire 1 & wr $end
$var reg 8 ) data_out [7:0] $end
$upscope $end
$upscope $end
$enddefinitions $end
$comment Show the parameter values. $end
$dumpall
$end
#0
$dumpvars
bx )
b0 (
b0 '
0&
1%
b0 $
0#
b0 "
bx !
$end
#5
b0 !
b0 )
1#
#10
0#
#15
1#
#20
0%
0#
#25
bx !
bx )
1#
#30
b1010 $
b1010 (
b1100111 "
b1100111 '
1&
0#
#35
1#
#40
b10000110 $
b10000110 (
b1101000 "
b1101000 '
0#
#45
1#
#50
b1100111 "
b1100111 '
0&
0#
#55
b1010 !
b1010 )
1#
#60
b11 "
b11 '
0#
#65
bx !
bx )
1#
#70
b1100110 $
b1100110 (
b1100111 "
b1100111 '
1&
0#
#75
1#
#80
0&
0#
#85
b1100110 !
b1100110 )
1#
